{
  "unversionedId": "tutorial-eli5/congratulations",
  "id": "tutorial-eli5/congratulations",
  "title": "Congratulations!",
  "description": "You have just learned the the basics of creating a simple recipe. But recipes can do much more than described in this first tutorial.",
  "source": "@site/docs/tutorial-eli5/06-congratulations.md",
  "sourceDirName": "tutorial-eli5",
  "slug": "/tutorial-eli5/congratulations",
  "permalink": "/ai-writer/docs/tutorial-eli5/congratulations",
  "draft": false,
  "editUrl": "https://github.com/svdoever/ai-writer/tree/main/docs/docs/tutorial-eli5/06-congratulations.md",
  "tags": [],
  "version": "current",
  "sidebarPosition": 99,
  "frontMatter": {
    "sidebar_position": 99
  },
  "sidebar": "docSidebar",
  "previous": {
    "title": "Executing the recipe",
    "permalink": "/ai-writer/docs/tutorial-eli5/executing-the-recipe"
  },
  "next": {
    "title": "Contributing",
    "permalink": "/ai-writer/docs/contributing"
  }
}